dcallme
