Metadata-Version: 1.1
Name: dcallme
Version: 0.0.1
Summary: dCall.me IP-PBX Cloud Service client
Home-page: https://github.com/swight/dcallme
Author: Stas D
Author-email: st@dcall.me
License: BSD
Keywords: dcallme ip pbx cloud service client
Platform: UNKNOWN
Classifier: Environment :: Web Environment
Classifier: Intended Audience :: Developers
Classifier: License :: OSI Approved :: BSD License
Classifier: Operating System :: OS Independent
Classifier: Programming Language :: Python
Classifier: Topic :: Internet :: WWW/HTTP :: Dynamic Content
Classifier: Topic :: Software Development :: Libraries :: Python Modules
